manage_requirements_files/__init__.py
manage_requirements_files/cli.py
manage_requirements_files-0.1.3.dist-info/LICENSE
manage_requirements_files-0.1.3.dist-info/METADATA
manage_requirements_files-0.1.3.dist-info/WHEEL
manage_requirements_files-0.1.3.dist-info/entry_points.txt
manage_requirements_files-0.1.3.dist-info/top_level.txt
manage_requirements_files-0.1.3.dist-info/RECORD
