Metadata-Version: 2.1
Name: manage_requirements_files
Version: 0.1.3
Summary: A utility to manage project dependencies for development and production.
Home-page: https://github.com/guilhermegouw/manage-requirements-files
Author: Guilherme Gouw
Author-email: guilherme.gouw@gmail.com
License: MIT
Classifier: Programming Language :: Python :: 3
Classifier: License :: OSI Approved :: MIT License
Classifier: Operating System :: OS Independent
Requires-Python: >=3.6
License-File: LICENSE
